Metadata-Version: 2.1
Name: sit-django-q
Version: 0.1.0
Summary: A multiprocessing distributed task queue for Django with modification for timezone aware schedules
Home-page: https://github.com/singularit-de/django-q
License: MIT
Keywords: django,distributed,multiprocessing,queue,scheduler,singularit
Author: Ilan Steemers
Author-email: koed00@gmail.com
Maintainer: Janek Mangold
Maintainer-email: janek.mangold@singular-it.de
Requires-Python: >=3.6.2,<4
Classifier: Development Status :: 5 - Production/Stable
Classifier: Environment :: Web Environment
Classifier: Framework :: Django
Classifier: Intended Audience :: Developers
Classifier: License :: OSI Approved :: MIT License
Classifier: Operating System :: MacOS
Classifier: Operating System :: POSIX
Classifier: Programming Language :: Python
Classifier: Programming Language :: Python :: 3
Classifier: Programming Language :: Python :: 3.7
Classifier: Programming Language :: Python :: 3.8
Classifier: Programming Language :: Python :: 3.9
Classifier: Programming Language :: Python :: 3.10
Classifier: Programming Language :: Python :: 3.11
Classifier: Programming Language :: Python :: 3
Classifier: Programming Language :: Python :: 3.6
Classifier: Programming Language :: Python :: 3.7
Classifier: Programming Language :: Python :: 3.8
Classifier: Programming Language :: Python :: 3.9
Classifier: Topic :: Internet :: WWW/HTTP
Classifier: Topic :: Software Development :: Libraries :: Python Modules
Classifier: Topic :: System :: Distributed Computing
Provides-Extra: build-backend
Provides-Extra: requires
Provides-Extra: rollbar
Provides-Extra: sentry
Provides-Extra: testing
Requires-Dist: arrow (>=1.1.0,<2.0.0)
Requires-Dist: blessed (>=1.17.6,<2.0.0)
Requires-Dist: boto3 (>=1.14.12,<2.0.0); extra == "testing"
Requires-Dist: croniter (>=0.3.34,<0.4.0); extra == "testing"
Requires-Dist: django (>=2.2)
Requires-Dist: django-picklefield (>=3.0.1,<4.0.0)
Requires-Dist: django-q-rollbar (>=0.1); extra == "rollbar"
Requires-Dist: django-q-sentry (>=0.1); extra == "sentry"
Requires-Dist: django-redis (>=4.12.1,<5.0.0); extra == "testing"
Requires-Dist: hiredis (>=1.0.1,<2.0.0); extra == "testing"
Requires-Dist: iron-mq (>=0.9,<0.10); extra == "testing"
Requires-Dist: psutil (>=5.7.0,<6.0.0); extra == "testing"
Requires-Dist: pymongo (>=3.10.1,<4.0.0); extra == "testing"
Requires-Dist: redis (>=3.5.3,<4.0.0)
Project-URL: Documentation, https://github.com/singularit-de/django-q
Project-URL: Repository, https://github.com/singularit-de/django-q
